{
  "ackermann": {
    "base_native": {
      "mean": 3251999.5,
      "median": 2936746.0,
      "min": 2911297.0,
      "max": 6125358.0,
      "std_dev": 1009698.494103314
    },
    "wasmtime_app": {
      "mean": 8780186.7,
      "median": 8627468.5,
      "min": 7954797.0,
      "max": 11909960.0,
      "std_dev": 1195267.2853929694
    }
  },
  "base64": {
    "base_native": {
      "mean": 253937741.66666666,
      "median": 253395161.0,
      "min": 253390736.0,
      "max": 255027328.0,
      "std_dev": 943612.0381260157
    },
    "wasmtime_app": {
      "mean": 355066147.0,
      "median": 355066147.0,
      "min": 350408277.0,
      "max": 359724017.0,
      "std_dev": 6587222.925770768
    }
  },
  "ctype": {
    "base_native": {
      "mean": 654438636.0,
      "median": 654438636.0,
      "min": 653715999.0,
      "max": 655161273.0,
      "std_dev": 1021963.0460726062
    },
    "wasmtime_app": {
      "mean": 986106246.0,
      "median": 986106246.0,
      "min": 986106246.0,
      "max": 986106246.0,
      "std_dev": 0.0
    }
  },
  "ed25519": {
    "base_native": {
      "mean": 1433211875.0,
      "median": 1433211875.0,
      "min": 1433211875.0,
      "max": 1433211875.0,
      "std_dev": 0.0
    },
    "wasmtime_app": {
      "mean": 6755365226.0,
      "median": 6755365226.0,
      "min": 6755365226.0,
      "max": 6755365226.0,
      "std_dev": 0.0
    }
  },
  "fib2": {
    "base_native": {
      "mean": 6956069904.0,
      "median": 6956069904.0,
      "min": 6956069904.0,
      "max": 6956069904.0,
      "std_dev": 0.0
    },
    "wasmtime_app": {
      "mean": 10686322524.0,
      "median": 10686322524.0,
      "min": 10686322524.0,
      "max": 10686322524.0,
      "std_dev": 0.0
    }
  },
  "gimli": {
    "base_native": {
      "mean": 4144737.9,
      "median": 4141065.5,
      "min": 4134978.0,
      "max": 4175202.0,
      "std_dev": 11359.244012892956
    },
    "wasmtime_app": {
      "mean": 9479699.0,
      "median": 9331938.0,
      "min": 9307015.0,
      "max": 10801022.0,
      "std_dev": 464606.42760991206
    }
  },
  "heapsort": {
    "base_native": {
      "mean": 1076198204.0,
      "median": 1076198204.0,
      "min": 1076198204.0,
      "max": 1076198204.0,
      "std_dev": 0.0
    },
    "wasmtime_app": {
      "mean": 1220349039.0,
      "median": 1220349039.0,
      "min": 1220349039.0,
      "max": 1220349039.0,
      "std_dev": 0.0
    }
  },
  "keccak": {
    "base_native": {
      "mean": 7479647.4,
      "median": 7478760.0,
      "min": 7468610.0,
      "max": 7493309.0,
      "std_dev": 7018.412200934213
    },
    "wasmtime_app": {
      "mean": 22888431.1,
      "median": 21303056.5,
      "min": 21008117.0,
      "max": 37281108.0,
      "std_dev": 5060188.863421831
    }
  },
  "matrix": {
    "base_native": {
      "mean": 377876219.5,
      "median": 377876219.5,
      "min": 377871007.0,
      "max": 377881432.0,
      "std_dev": 7371.588193869758
    },
    "wasmtime_app": {
      "mean": 533732738.0,
      "median": 533732738.0,
      "min": 529373657.0,
      "max": 538091819.0,
      "std_dev": 6164671.469682873
    }
  },
  "matrix2": {
    "base_native": {
      "mean": 194267983.5,
      "median": 194261977.5,
      "min": 194254028.0,
      "max": 194293951.0,
      "std_dev": 17925.63907740344
    },
    "wasmtime_app": {
      "mean": 260172738.66666666,
      "median": 257651571.0,
      "min": 257632972.0,
      "max": 265233673.0,
      "std_dev": 4382907.565239579
    }
  },
  "memmove": {
    "base_native": {
      "mean": 47329350.1,
      "median": 47327712.5,
      "min": 47314951.0,
      "max": 47357649.0,
      "std_dev": 11584.622244356717
    },
    "wasmtime_app": {
      "mean": 520715327.5,
      "median": 520715327.5,
      "min": 515954591.0,
      "max": 525476064.0,
      "std_dev": 6732698.12518462
    }
  },
  "minicsv": {
    "base_native": {
      "mean": 748860459.0,
      "median": 748860459.0,
      "min": 748860459.0,
      "max": 748860459.0,
      "std_dev": 0.0
    },
    "wasmtime_app": {
      "mean": 1099003163.0,
      "median": 1099003163.0,
      "min": 1099003163.0,
      "max": 1099003163.0,
      "std_dev": 0.0
    }
  },
  "nestedloop": {
    "base_native": {
      "mean": 1575898.5454545454,
      "median": 1580394.0,
      "min": 1554145.0,
      "max": 1602243.0,
      "std_dev": 18189.08128171204
    },
    "wasmtime_app": {
      "mean": 6252516.1,
      "median": 6160126.0,
      "min": 6139590.0,
      "max": 7076741.0,
      "std_dev": 290075.64181221195
    }
  },
  "nestedloop2": {
    "base_native": {
      "mean": 1587145.6363636365,
      "median": 1585018.0,
      "min": 1552670.0,
      "max": 1627417.0,
      "std_dev": 19414.648738891607
    },
    "wasmtime_app": {
      "mean": 6257370.8,
      "median": 6178487.0,
      "min": 6166038.0,
      "max": 6947676.0,
      "std_dev": 242930.64435705374
    }
  },
  "nestedloop3": {
    "base_native": {
      "mean": 2088041.5454545454,
      "median": 2087701.0,
      "min": 2065276.0,
      "max": 2098350.0,
      "std_dev": 9164.738516331347
    },
    "wasmtime_app": {
      "mean": 6840687.4,
      "median": 6712995.0,
      "min": 6690897.0,
      "max": 7913575.0,
      "std_dev": 378058.59246424295
    }
  },
  "random": {
    "base_native": {
      "mean": 577580055.0,
      "median": 577580055.0,
      "min": 577569293.0,
      "max": 577590817.0,
      "std_dev": 15219.766358259249
    },
    "wasmtime_app": {
      "mean": 290683581.3333333,
      "median": 290425035.0,
      "min": 290371189.0,
      "max": 291254520.0,
      "std_dev": 495179.83475736703
    }
  },
  "random2": {
    "base_native": {
      "mean": 577652627.5,
      "median": 577652627.5,
      "min": 577577393.0,
      "max": 577727862.0,
      "std_dev": 106397.65025835863
    },
    "wasmtime_app": {
      "mean": 290683414.3333333,
      "median": 290394862.0,
      "min": 290393512.0,
      "max": 291261869.0,
      "std_dev": 500956.8910258979
    }
  },
  "ratelimit": {
    "base_native": {
      "mean": 25945936.7,
      "median": 25941282.0,
      "min": 25908733.0,
      "max": 25997330.0,
      "std_dev": 27536.80655676043
    },
    "wasmtime_app": {
      "mean": 39056705.3,
      "median": 38335237.5,
      "min": 38303152.0,
      "max": 45594377.0,
      "std_dev": 2297149.24251986
    }
  },
  "seqhash": {
    "base_native": {
      "mean": 7105056508.0,
      "median": 7105056508.0,
      "min": 7105056508.0,
      "max": 7105056508.0,
      "std_dev": 0.0
    },
    "wasmtime_app": {
      "mean": 9681190904.0,
      "median": 9681190904.0,
      "min": 9681190904.0,
      "max": 9681190904.0,
      "std_dev": 0.0
    }
  },
  "sieve": {
    "base_native": {
      "mean": 569276136.0,
      "median": 569276136.0,
      "min": 569275636.0,
      "max": 569276636.0,
      "std_dev": 707.1067811865476
    },
    "wasmtime_app": {
      "mean": 767237564.0,
      "median": 767237564.0,
      "min": 767237564.0,
      "max": 767237564.0,
      "std_dev": 0.0
    }
  },
  "strcat": {
    "base_native": {
      "mean": 65846400.1,
      "median": 65838882.5,
      "min": 65830946.0,
      "max": 65924442.0,
      "std_dev": 27860.527439571404
    },
    "wasmtime_app": {
      "mean": 348205251.0,
      "median": 348205251.0,
      "min": 341243600.0,
      "max": 355166902.0,
      "std_dev": 9845261.26070822
    }
  },
  "strcat2": {
    "base_native": {
      "mean": 2588494.1818181816,
      "median": 2584158.0,
      "min": 2576208.0,
      "max": 2613207.0,
      "std_dev": 10884.794677146481
    },
    "wasmtime_app": {
      "mean": 9266603.4,
      "median": 8458632.0,
      "min": 7951997.0,
      "max": 17635458.0,
      "std_dev": 2946938.9814198054
    }
  },
  "strchr": {
    "base_native": {
      "mean": 154939908.4,
      "median": 155025815.0,
      "min": 154703227.0,
      "max": 155086213.0,
      "std_dev": 159722.1948252653
    },
    "wasmtime_app": {
      "mean": 406696636.0,
      "median": 406696636.0,
      "min": 402284284.0,
      "max": 411108988.0,
      "std_dev": 6240008.04036405
    }
  },
  "strlen": {
    "base_native": {
      "mean": 47722693.8,
      "median": 47697187.5,
      "min": 47545918.0,
      "max": 47967403.0,
      "std_dev": 130043.93926481582
    },
    "wasmtime_app": {
      "mean": 218979872.0,
      "median": 216898961.5,
      "min": 216858189.0,
      "max": 225263376.0,
      "std_dev": 4189052.077874182
    }
  },
  "strtok": {
    "base_native": {
      "mean": 374205049.5,
      "median": 374205049.5,
      "min": 374203862.0,
      "max": 374206237.0,
      "std_dev": 1679.3786053180504
    },
    "wasmtime_app": {
      "mean": 1220942517.0,
      "median": 1220942517.0,
      "min": 1220942517.0,
      "max": 1220942517.0,
      "std_dev": 0.0
    }
  },
  "switch": {
    "base_native": {
      "mean": 52304604.3,
      "median": 52295737.0,
      "min": 52259901.0,
      "max": 52366147.0,
      "std_dev": 41430.07568596085
    },
    "wasmtime_app": {
      "mean": 63199832.9,
      "median": 59182680.0,
      "min": 59152107.0,
      "max": 99347636.0,
      "std_dev": 12701058.28688478
    }
  },
  "switch2": {
    "base_native": {
      "mean": 1452669036.0,
      "median": 1452669036.0,
      "min": 1452669036.0,
      "max": 1452669036.0,
      "std_dev": 0.0
    },
    "wasmtime_app": {
      "mean": 292653634.3333333,
      "median": 268565660.0,
      "min": 268546761.0,
      "max": 340848482.0,
      "std_dev": 41737963.48054077
    }
  },
  "xblabla20": {
    "base_native": {
      "mean": 3042653.272727273,
      "median": 3045342.0,
      "min": 3024393.0,
      "max": 3058466.0,
      "std_dev": 11066.275480855418
    },
    "wasmtime_app": {
      "mean": 13245714.3,
      "median": 9721245.0,
      "min": 9667387.0,
      "max": 44965077.0,
      "std_dev": 11145100.526135461
    }
  },
  "xchacha20": {
    "base_native": {
      "mean": 4184696.4,
      "median": 4188313.5,
      "min": 4157802.0,
      "max": 4205451.0,
      "std_dev": 14188.566376566107
    },
    "wasmtime_app": {
      "mean": 11074745.6,
      "median": 10077679.5,
      "min": 10050706.0,
      "max": 20026869.0,
      "std_dev": 3145570.515167221
    }
  }
}